aixploit/__init__.py
aixploit/core.py
aixploit/instrumentalize/__init__.py
aixploit/instrumentalize/deepseek.py
aixploit/instrumentalize/ollama.py
aixploit/instrumentalize/openai.py
aixploit/instrumentalize/validation.py
aixploit/plugins/__init__.py
aixploit/plugins/base.py
aixploit/plugins/abuse/Abuse.py
aixploit/plugins/abuse/__init__.py
aixploit/plugins/availability/Availability.py
aixploit/plugins/availability/__init__.py
aixploit/plugins/integrity/Code.py
aixploit/plugins/integrity/DirectPromptInjection.py
aixploit/plugins/integrity/IndirectPromptInjection.py
aixploit/plugins/integrity/Integrity.py
aixploit/plugins/integrity/Language.py
aixploit/plugins/integrity/Topics.py
aixploit/plugins/integrity/__init__.py
aixploit/plugins/privacy/Privacy.py
aixploit/plugins/privacy/__init__.py
attack_prompts/__init__.py
attack_prompts/custom_scan_payloads-.yaml
attack_prompts/custom_scan_payloads.yaml
attack_prompts/full_scan_payloads.yaml
attack_prompts/quick_scan_payloads.yaml
attack_responses/__init__.py
aixploit-1.2.8.3.dist-info/LICENSE
aixploit-1.2.8.3.dist-info/METADATA
aixploit-1.2.8.3.dist-info/WHEEL
aixploit-1.2.8.3.dist-info/top_level.txt
aixploit-1.2.8.3.dist-info/RECORD
