Metadata-Version: 2.1
Name: aixploit
Version: 1.2.8.3
Summary: AI redTeaming Python library
Home-page: https://github.com/AINTRUST-AI/AIxploit
Author: aintrust
Author-email: aintrust <contact@aintrust.ai>
License: GPL-3.0
Keywords: AI,redteaming,AI redteaming,AI redteam,AI redteaming library,AI redteam library,LLM Guardrails,LLM Security,LLM,LLMs
Classifier: Programming Language :: Python :: 3
Classifier: License :: OSI Approved :: GNU General Public License v3 (GPLv3)
Classifier: Operating System :: OS Independent
Requires-Python: >=3.9
License-File: LICENSE
Requires-Dist: openai==1.56.0
Requires-Dist: tiktoken==0.8.0
Requires-Dist: sentence-transformers==3.3.1
Requires-Dist: pyyaml==6.0.2
Requires-Dist: tqdm==4.66.6
Requires-Dist: numpy==2.0.1
